[
  {
    "ID": 16652,
    "Photo": "http://makerfaire.files.wordpress.com/2013/09/nysci-color-logo-reduced-size7.jpg"
  },
  {
    "ID": 16575,
    "Photo": "http://makerfaire.files.wordpress.com/2013/09/salt-flats-8858.jpg"
  },
  {
    "ID": 16447,
    "Photo": "http://makerfaire.files.wordpress.com/2013/09/16447.jpg"
  },
  {
    "ID": 16443,
    "Photo": "http://makerfaire.files.wordpress.com/2013/09/16443.jpg"
  },
  {
    "ID": 16439,
    "Photo": "http://makerfaire.files.wordpress.com/2013/09/16439.jpg"
  },
  {
    "ID": 16435,
    "Photo": "http://makerfaire.files.wordpress.com/2013/09/16435.jpg"
  },
  {
    "ID": 16426,
    "Photo": "http://makerfaire.files.wordpress.com/2013/09/16426.jpg"
  },
  {
    "ID": 16427,
    "Photo": "http://makerfaire.files.wordpress.com/2013/09/16427.jpg"
  },
  {
    "ID": 16428,
    "Photo": "http://makerfaire.files.wordpress.com/2013/09/16428.jpg"
  },
  {
    "ID": 16429,
    "Photo": "http://makerfaire.files.wordpress.com/2013/09/16429.jpg"
  },
  {
    "ID": 16430,
    "Photo": "http://makerfaire.files.wordpress.com/2013/09/16430.jpg"
  },
  {
    "ID": 16431,
    "Photo": "http://makerfaire.files.wordpress.com/2013/09/16431.png"
  },
  {
    "ID": 16432,
    "Photo": "http://makerfaire.files.wordpress.com/2013/09/16432.jpg"
  },
  {
    "ID": 16418,
    "Photo": "http://makerfaire.files.wordpress.com/2013/09/16418.jpg"
  },
  {
    "ID": 16419,
    "Photo": "http://makerfaire.files.wordpress.com/2013/09/16419.jpg"
  },
  {
    "ID": 16420,
    "Photo": "http://makerfaire.files.wordpress.com/2013/09/16420.jpg"
  },
  {
    "ID": 16421,
    "Photo": "http://makerfaire.files.wordpress.com/2013/09/16421.jpg"
  },
  {
    "ID": 16422,
    "Photo": "http://makerfaire.files.wordpress.com/2013/09/16422.png"
  },
  {
    "ID": 16423,
    "Photo": "http://makerfaire.files.wordpress.com/2013/09/16423.jpg"
  },
  {
    "ID": 16424,
    "Photo": "http://makerfaire.files.wordpress.com/2013/09/16424.jpg"
  },
  {
    "ID": 16425,
    "Photo": "http://makerfaire.files.wordpress.com/2013/09/16425.jpg"
  },
  {
    "ID": 16407,
    "Photo": "http://img0.etsystatic.com/000/0/5677834/il_570xN.344528172.jpg"
  },
  {
    "ID": 16408,
    "Photo": "http://makerfaire.files.wordpress.com/2013/09/16408.jpg"
  },
  {
    "ID": 16409,
    "Photo": "http://www.queenbeefibers.com/wp-content/uploads/2012/09/17.jpg"
  },
  {
    "ID": 16410,
    "Photo": "http://www.fleursjolies.com/images/photo_lace.jpg"
  },
  {
    "ID": 16411,
    "Photo": "http://loopoftheloom.com/waterfall_yu3.jpg"
  },
  {
    "ID": 16412,
    "Photo": "http://themefiendlab.com/hosting/images/kellyhorrigan/home-banner-01.jpg"
  },
  {
    "ID": 16413,
    "Photo": "https://fbcdn-sphotos-d-a.akamaihd.net/hphotos-ak-ash3/149004_453695899345_4239309_n.jpg"
  },
  {
    "ID": 16414,
    "Photo": "http://www.doreenbaskin.com/Doreen_Baskin_files/Doreen%20Baskin%20Slide%203.jpg"
  },
  {
    "ID": 16415,
    "Photo": "http://img1.etsystatic.com/000/0/6442983/il_570xN.313707327.jpg"
  },
  {
    "ID": 16416,
    "Photo": "https://sphotos-b-lga.xx.fbcdn.net/hphotos-ash4/306585_284894134918750_1684968625_n.jpg"
  },
  {
    "ID": 16417,
    "Photo": "http://makerfaire.files.wordpress.com/2013/09/16417.jpg"
  },
  {
    "ID": 16400,
    "Photo": "http://thevintagerobot.files.wordpress.com/2013/08/photo-12.jpg"
  },
  {
    "ID": 16401,
    "Photo": "http://makerfaire.files.wordpress.com/2013/09/16401.jpeg"
  },
  {
    "ID": 16402,
    "Photo": "http://makerfaire.files.wordpress.com/2013/09/16402.jpg"
  },
  {
    "ID": 16403,
    "Photo": "http://makerfaire.files.wordpress.com/2013/09/screen-shot-2013-09-05-at-9-02-24-pm.png"
  },
  {
    "ID": 16404,
    "Photo": "http://i28.photobucket.com/albums/c237/peteyorko003/mr%20photos/edited/witchdoctorring_zps6ed97e8f.jpg"
  },
  {
    "ID": 16405,
    "Photo": "http://www.zoachimerum.com/gallery/wp-content/uploads/chelicerae_necklace1.jpg"
  },
  {
    "ID": 16406,
    "Photo": "http://thechocolateswirl.com/wp-content/gallery/brownie-pops_1/brownie_pop_assortments.jpg"
  },
  {
    "ID": 16391,
    "Photo": "http://i1215.photobucket.com/albums/cc508/ItsMariaAlyssa/June%202013/Shopbevel/shopbevel_zps5d0a4020.jpg"
  },
  {
    "ID": 16392,
    "Photo": "http://makerfaire.files.wordpress.com/2013/09/163922.jpg"
  },
  {
    "ID": 16393,
    "Photo": "http://img1.etsystatic.com/000/0/6115074/il_570xN.281957711.jpg"
  },
  {
    "ID": 16394,
    "Photo": "http://makerfaire.files.wordpress.com/2013/09/16394.jpg"
  },
  {
    "ID": 16395,
    "Photo": "http://images.cdn.bigcartel.com/bigcartel/product_images/59134991/max_h-1000+max_w-1000/Necklace_Tusk_Gold_A.jpg"
  },
  {
    "ID": 16396,
    "Photo": "https://fbcdn-sphotos-g-a.akamaihd.net/hphotos-ak-ash4/1039818_556076544434564_726066077_o.jpg"
  },
  {
    "ID": 16397,
    "Photo": "http://dpegb9ebondhq.cloudfront.net/product_photos/849473/ive-just-developed-a-theory_tee-black_large.jpg"
  },
  {
    "ID": 16398,
    "Photo": "http://makerfaire.files.wordpress.com/2013/09/16398.jpg"
  },
  {
    "ID": 16399,
    "Photo": "http://www.iloveumsteigen.com/images/2013-springgallery.jpg"
  },
  {
    "ID": 16384,
    "Photo": "http://www.dollsvillenyc.com/data/images1/dollsvillenycredveil.jpg"
  },
  {
    "ID": 16385,
    "Photo": "http://media.denadadesign.webfactional.com/images/collection2012/DeNada_Lookbook_2012_01.jpg"
  },
  {
    "ID": 16386,
    "Photo": "http://potus31.com/images/Wonder_Wheel_front2.jpg"
  },
  {
    "ID": 16387,
    "Photo": "http://cdn.shopify.com/s/files/1/0131/6682/products/KH_M_1_large.jpg?666"
  },
  {
    "ID": 16388,
    "Photo": "http://img0.etsystatic.com/002/0/5366552/il_570xN.397203542_dicg.jpg"
  },
  {
    "ID": 16389,
    "Photo": "http://images.cdn.bigcartel.com/bigcartel/product_images/121451592/max_h-1000+max_w-1000/jaws_cropped.jpg"
  },
  {
    "ID": 16390,
    "Photo": "https://sphotos-a-lga.xx.fbcdn.net/hphotos-prn1/150445_557181737655409_956233059_n.jpg"
  },
  {
    "ID": 16373,
    "Photo": "https://sphotos-b-lga.xx.fbcdn.net/hphotos-prn2/179736_10151658929751808_225789150_n.jpg"
  },
  {
    "ID": 16374,
    "Photo": "https://fbcdn-sphotos-g-a.akamaihd.net/hphotos-ak-prn1/884925_429064220514246_673965623_o.jpg"
  },
  {
    "ID": 16375,
    "Photo": "http://2.bp.blogspot.com/-B8JYLGstqhc/UeCKnyZdbUI/AAAAAAAABC0/PSxCrxHrKbE/s640/20130606_SG_Zod_Cancer_0005.jpg"
  },
  {
    "ID": 16376,
    "Photo": "https://img1.etsystatic.com/018/1/8008746/il_fullxfull.490730403_ff98.jpg?ref=l2"
  },
  {
    "ID": 16377,
    "Photo": "http://img1.etsystatic.com/008/0/6252085/il_570xN.385100207_qc54.jpg"
  },
  {
    "ID": 16378,
    "Photo": "http://static.squarespace.com/static/51671fe1e4b0d248167c4d12/t/51f315ade4b00513cb65b185/1374885303721/4BEST.JPG?format=1000w"
  },
  {
    "ID": 16380,
    "Photo": "http://www.creativedexterity.com/Geometric/Geometric/VNecklace_files/stacks_image_8625.jpg"
  },
  {
    "ID": 16381,
    "Photo": "https://sphotos-a-lga.xx.fbcdn.net/hphotos-ash3/154288_171356712898182_2686973_n.jpg"
  },
  {
    "ID": 16382,
    "Photo": "http://makerfaire.files.wordpress.com/2013/09/16382.jpeg"
  },
  {
    "ID": 16383,
    "Photo": "http://img0.etsystatic.com/008/0/5177581/il_570xN.399504418_qw3g.jpg"
  },
  {
    "ID": 16365,
    "Photo": "http://u.jimdo.com/www21/o/s73d9bbcc903e0a99/img/i83082a109865f27d/1369419270/std/image.jpg"
  },
  {
    "ID": 16366,
    "Photo": "http://img0.etsystatic.com/004/1/5842032/il_570xN.379957624_1ljt.jpg"
  },
  {
    "ID": 16367,
    "Photo": "http://ep.yimg.com/ca/I/yhst-61408801214813_2270_0"
  },
  {
    "ID": 16368,
    "Photo": "http://andreabocchio.com/wp-content/uploads/2013/07/Asi-copy.jpg"
  },
  {
    "ID": 16371,
    "Photo": "http://makerfaire.files.wordpress.com/2013/09/16371.jpg"
  },
  {
    "ID": 16372,
    "Photo": "https://sphotos-a-lga.xx.fbcdn.net/hphotos-ash3/226668_498884293531312_467980082_n.jpg"
  },
  {
    "ID": 16344,
    "Photo": "http://makerfaire.files.wordpress.com/2013/09/simple.jpeg"
  },
  {
    "ID": 16266,
    "Photo": "http://makerfaire.files.wordpress.com/2013/09/bigshot_front.jpg"
  },
  {
    "ID": 16011,
    "Photo": "http://makerfaire.files.wordpress.com/2013/09/emerging.jpg"
  },
  {
    "ID": 15957,
    "Photo": "http://makerfaire.files.wordpress.com/2013/09/rorshack.png"
  },
  {
    "ID": 15950,
    "Photo": "http://makerfaire.files.wordpress.com/2013/09/july-evening.png"
  },
  {
    "ID": 15944,
    "Photo": "http://makerfaire.files.wordpress.com/2013/09/drama-in-the-garden.png"
  },
  {
    "ID": 15937,
    "Photo": "http://makerfaire.files.wordpress.com/2013/09/don-cornelius.png"
  },
  {
    "ID": 15904,
    "Photo": "http://makerfaire.files.wordpress.com/2013/09/beatty.jpg"
  },
  {
    "ID": 15898,
    "Photo": "http://makerfaire.files.wordpress.com/2013/09/dry-ice-bubbles.jpg"
  },
  {
    "ID": 15891,
    "Photo": "http://makerfaire.files.wordpress.com/2013/09/explainer-demos.jpg"
  },
  {
    "ID": 15808,
    "Photo": "http://makerfaire.files.wordpress.com/2013/09/946840_10151584201489947_168074444_n.jpg"
  },
  {
    "ID": 15680,
    "Photo": "http://makerfaire.files.wordpress.com/2013/08/design-lab_motion.jpg"
  },
  {
    "ID": 15675,
    "Photo": "http://makerfaire.files.wordpress.com/2013/08/design-lab.jpg"
  },
  {
    "ID": 15665,
    "Photo": "http://makerfaire.files.wordpress.com/2013/08/melting-man.jpeg"
  },
  {
    "ID": 15648,
    "Photo": "http://makerfaire.files.wordpress.com/2013/08/cosee-ocean-1.jpg"
  },
  {
    "ID": 15640,
    "Photo": "http://makerfaire.files.wordpress.com/2013/08/sciplay-1.jpg"
  },
  {
    "ID": 15632,
    "Photo": "http://makerfaire.files.wordpress.com/2013/08/maker-space.jpg"
  },
  {
    "ID": 15627,
    "Photo": "http://makerfaire.files.wordpress.com/2013/08/little-makers.jpg"
  },
  {
    "ID": 15620,
    "Photo": "http://makerfaire.files.wordpress.com/2013/08/library-copy.jpg"
  },
  {
    "ID": 15603,
    "Photo": "http://makerfaire.files.wordpress.com/2013/08/medik.png"
  },
  {
    "ID": 15601,
    "Photo": "http://makerfaire.files.wordpress.com/2013/08/craftstudio2.png"
  },
  {
    "ID": 15599,
    "Photo": "http://makerfaire.files.wordpress.com/2013/08/casebeereeg1.jpg"
  },
  {
    "ID": 15573,
    "Photo": "http://makerfaire.files.wordpress.com/2013/08/spinbots-overhead.jpg"
  },
  {
    "ID": 15567,
    "Photo": "http://makerfaire.files.wordpress.com/2013/08/20130705_113506_12.jpg"
  },
  {
    "ID": 15527,
    "Photo": "http://makerfaire.files.wordpress.com/2013/08/wnl_logo_v1-013.png"
  },
  {
    "ID": 15384,
    "Photo": "http://makerfaire.files.wordpress.com/2013/08/detroit-team.jpg"
  },
  {
    "ID": 15379,
    "Photo": "http://makerfaire.files.wordpress.com/2013/08/howdo1.png"
  },
  {
    "ID": 15348,
    "Photo": "http://makerfaire.files.wordpress.com/2013/08/2012makerfaire.jpg"
  },
  {
    "ID": 15278,
    "Photo": "http://makerfaire.files.wordpress.com/2013/08/swap-bmf-2013.jpg"
  },
  {
    "ID": 14764,
    "Photo": "http://makerfaire.files.wordpress.com/2013/08/282437_10150400234968572_537473571_10552725_6605500_a.jpg"
  },
  {
    "ID": 14700,
    "Photo": "http://makerfaire.files.wordpress.com/2013/08/p1000066.jpg"
  },
  {
    "ID": 14597,
    "Photo": "http://makerfaire.files.wordpress.com/2013/08/1146656_10151561794546695_1679243089_n.jpg"
  },
  {
    "ID": 14574,
    "Photo": "http://makerfaire.files.wordpress.com/2013/08/image7.jpg"
  },
  {
    "ID": 14572,
    "Photo": "http://makerfaire.files.wordpress.com/2013/08/display.jpg"
  },
  {
    "ID": 14566,
    "Photo": "http://makerfaire.files.wordpress.com/2013/08/fubarlogo.png"
  },
  {
    "ID": 14498,
    "Photo": "http://makerfaire.files.wordpress.com/2013/08/20121125_183529.jpg"
  },
  {
    "ID": 14412,
    "Photo": "http://makerfaire.files.wordpress.com/2013/08/bust-magazine-craftacular-logo-cube.gif"
  },
  {
    "ID": 14309,
    "Photo": "http://makerfaire.files.wordpress.com/2013/08/tape.jpg"
  },
  {
    "ID": 14284,
    "Photo": "http://makerfaire.files.wordpress.com/2013/08/banshee-detroit.jpg"
  },
  {
    "ID": 14267,
    "Photo": "http://makerfaire.files.wordpress.com/2013/08/images.jpg"
  },
  {
    "ID": 14159,
    "Photo": "http://makerfaire.files.wordpress.com/2013/08/nerdyderby2012.jpg"
  },
  {
    "ID": 14135,
    "Photo": "http://makerfaire.files.wordpress.com/2013/08/eqp2xoonqhybk4w-o0kvhbt3ehgvsyfbhbmau7q5c6k.jpeg"
  },
  {
    "ID": 14060,
    "Photo": "http://makerfaire.files.wordpress.com/2013/08/stabilgo-twitter-icon.jpg"
  },
  {
    "ID": 14035,
    "Photo": "http://makerfaire.files.wordpress.com/2013/08/mrkim-printer-v7-0-0-6483-s.jpg"
  },
  {
    "ID": 14030,
    "Photo": "http://makerfaire.files.wordpress.com/2013/08/r2ny-mainlogo.jpg"
  },
  {
    "ID": 13851,
    "Photo": "http://makerfaire.files.wordpress.com/2013/08/img_0051.jpg"
  },
  {
    "ID": 13844,
    "Photo": "http://makerfaire.files.wordpress.com/2013/08/img_4066.jpg"
  },
  {
    "ID": 13809,
    "Photo": "http://makerfaire.files.wordpress.com/2013/08/capture.jpg"
  },
  {
    "ID": 13755,
    "Photo": "http://makerfaire.files.wordpress.com/2013/08/img_3669.jpg"
  },
  {
    "ID": 13714,
    "Photo": "http://makerfaire.files.wordpress.com/2013/08/maria.png"
  },
  {
    "ID": 13706,
    "Photo": "http://makerfaire.files.wordpress.com/2013/08/for_print2.jpg"
  },
  {
    "ID": 13685,
    "Photo": "http://makerfaire.files.wordpress.com/2013/08/img_2028.jpg"
  },
  {
    "ID": 13677,
    "Photo": "http://makerfaire.files.wordpress.com/2013/08/morsesserettelegraph.jpg"
  },
  {
    "ID": 13626,
    "Photo": "http://makerfaire.files.wordpress.com/2013/08/yesnow-project-photo.jpg"
  },
  {
    "ID": 13617,
    "Photo": "http://makerfaire.files.wordpress.com/2013/08/tinyduinotindie.png"
  },
  {
    "ID": 13376,
    "Photo": ""
  },
  {
    "ID": 13341,
    "Photo": "http://makerfaire.files.wordpress.com/2013/08/rc-front-hires.jpg"
  },
  {
    "ID": 13334,
    "Photo": "http://makerfaire.files.wordpress.com/2013/08/blue.jpg"
  },
  {
    "ID": 13313,
    "Photo": ""
  },
  {
    "ID": 13293,
    "Photo": "http://makerfaire.files.wordpress.com/2013/08/8107645350_1fee70f5fc_k.jpg"
  },
  {
    "ID": 13286,
    "Photo": "http://makerfaire.files.wordpress.com/2013/08/t_max_2-01.jpg"
  },
  {
    "ID": 13200,
    "Photo": "http://makerfaire.files.wordpress.com/2013/08/2011-05-21_17-57-36.jpg"
  },
  {
    "ID": 13175,
    "Photo": "http://makerfaire.files.wordpress.com/2013/08/logo_e1.jpg"
  },
  {
    "ID": 13136,
    "Photo": "http://makerfaire.files.wordpress.com/2013/08/image2.jpg"
  },
  {
    "ID": 13104,
    "Photo": "http://makerfaire.files.wordpress.com/2013/08/flat-bangle-c.jpg"
  },
  {
    "ID": 13051,
    "Photo": "http://makerfaire.files.wordpress.com/2013/08/main_makerfaire02.jpg"
  },
  {
    "ID": 13047,
    "Photo": "http://makerfaire.files.wordpress.com/2013/08/img_9726.jpg"
  },
  {
    "ID": 13026,
    "Photo": "http://makerfaire.files.wordpress.com/2013/08/circle-in-a-square.png"
  },
  {
    "ID": 13022,
    "Photo": "http://makerfaire.files.wordpress.com/2013/08/hackruhackny2013.jpg"
  },
  {
    "ID": 13017,
    "Photo": "http://makerfaire.files.wordpress.com/2013/08/dpic5_sml.jpg"
  },
  {
    "ID": 13015,
    "Photo": "http://makerfaire.files.wordpress.com/2013/08/kids-in-lab-version-3.jpg"
  },
  {
    "ID": 12993,
    "Photo": "http://makerfaire.files.wordpress.com/2013/08/watercolorbot_promo.jpg"
  },
  {
    "ID": 12967,
    "Photo": "http://makerfaire.files.wordpress.com/2013/08/dsc00905.jpg"
  },
  {
    "ID": 12965,
    "Photo": "http://makerfaire.files.wordpress.com/2013/08/public-panopticon-powder_1000px.jpg"
  },
  {
    "ID": 12947,
    "Photo": "http://makerfaire.files.wordpress.com/2013/08/maker_faire_img.jpg"
  },
  {
    "ID": 12935,
    "Photo": "http://makerfaire.files.wordpress.com/2013/08/robotichandkitpicmakerfairecontest.jpg"
  },
  {
    "ID": 12933,
    "Photo": "http://makerfaire.files.wordpress.com/2013/08/project_blink_ethernet_banner.png"
  },
  {
    "ID": 12923,
    "Photo": "http://makerfaire.files.wordpress.com/2013/08/refined.jpg"
  },
  {
    "ID": 12903,
    "Photo": "http://makerfaire.files.wordpress.com/2013/08/jg-exhibits.jpg"
  },
  {
    "ID": 12896,
    "Photo": "http://makerfaire.files.wordpress.com/2013/08/brf_logo-1.jpg"
  },
  {
    "ID": 12891,
    "Photo": "http://makerfaire.files.wordpress.com/2013/08/popcade.png"
  },
  {
    "ID": 12882,
    "Photo": "http://makerfaire.files.wordpress.com/2013/08/dscn0594.jpg"
  },
  {
    "ID": 12872,
    "Photo": "http://makerfaire.files.wordpress.com/2013/08/dogbottledrinking.jpg"
  },
  {
    "ID": 12848,
    "Photo": "http://makerfaire.files.wordpress.com/2013/08/margolis_01_web.jpg"
  },
  {
    "ID": 12816,
    "Photo": "http://makerfaire.files.wordpress.com/2013/08/maker.png"
  },
  {
    "ID": 12725,
    "Photo": "http://makerfaire.files.wordpress.com/2013/08/shelter201.png"
  },
  {
    "ID": 12668,
    "Photo": "http://makerfaire.files.wordpress.com/2013/08/screen-shot-2013-08-03-at-11-31-36-pm.png"
  },
  {
    "ID": 12597,
    "Photo": "http://makerfaire.files.wordpress.com/2013/08/ig_robo_heart.jpg"
  },
  {
    "ID": 12586,
    "Photo": "http://makerfaire.files.wordpress.com/2013/08/projectphoto.jpg"
  },
  {
    "ID": 12581,
    "Photo": "http://makerfaire.files.wordpress.com/2013/08/ferrari.jpg"
  },
  {
    "ID": 12572,
    "Photo": "http://makerfaire.files.wordpress.com/2013/08/dsc_1415-small.jpg"
  },
  {
    "ID": 12565,
    "Photo": "http://makerfaire.files.wordpress.com/2013/08/jefffrankenbike.jpg"
  },
  {
    "ID": 12553,
    "Photo": "http://makerfaire.files.wordpress.com/2013/08/image.jpg"
  },
  {
    "ID": 12542,
    "Photo": "http://makerfaire.files.wordpress.com/2013/08/img_3232.jpg"
  },
  {
    "ID": 12522,
    "Photo": "http://makerfaire.files.wordpress.com/2013/08/arduino_due_in_hand.jpg"
  },
  {
    "ID": 12511,
    "Photo": "http://makerfaire.files.wordpress.com/2013/08/augmented_carousel.jpg"
  },
  {
    "ID": 12503,
    "Photo": "http://makerfaire.files.wordpress.com/2013/08/othermill-product1.jpg"
  },
  {
    "ID": 12467,
    "Photo": "http://makerfaire.files.wordpress.com/2013/08/sidelogo-zahncenter.jpg"
  },
  {
    "ID": 12465,
    "Photo": "http://makerfaire.files.wordpress.com/2013/08/telegraph_decoder.jpg"
  },
  {
    "ID": 12450,
    "Photo": "http://makerfaire.files.wordpress.com/2013/08/bettytkao-dress.jpg"
  },
  {
    "ID": 12429,
    "Photo": "http://makerfaire.files.wordpress.com/2013/08/img_0137.jpg"
  },
  {
    "ID": 12420,
    "Photo": "http://makerfaire.files.wordpress.com/2013/08/img_7038.jpg"
  },
  {
    "ID": 12415,
    "Photo": "http://makerfaire.files.wordpress.com/2013/08/dsc_0175.jpg"
  },
  {
    "ID": 12409,
    "Photo": "http://makerfaire.files.wordpress.com/2013/08/img_47061.jpg"
  },
  {
    "ID": 12404,
    "Photo": "http://makerfaire.files.wordpress.com/2013/08/owl-platform2.png"
  },
  {
    "ID": 12390,
    "Photo": "http://makerfaire.files.wordpress.com/2013/07/portalcade.jpg"
  },
  {
    "ID": 12373,
    "Photo": "http://makerfaire.files.wordpress.com/2013/07/dsc0791_2400.jpg"
  },
  {
    "ID": 12366,
    "Photo": "http://makerfaire.files.wordpress.com/2013/07/abcollage.jpg"
  },
  {
    "ID": 12359,
    "Photo": "http://makerfaire.files.wordpress.com/2013/07/603983_376857505732570_874614518_n.jpg"
  },
  {
    "ID": 12352,
    "Photo": "http://makerfaire.files.wordpress.com/2013/07/2-copy-3.jpg"
  },
  {
    "ID": 12349,
    "Photo": "http://makerfaire.files.wordpress.com/2013/07/makerfaire.jpg"
  },
  {
    "ID": 12347,
    "Photo": "http://makerfaire.files.wordpress.com/2013/07/img_2040.jpg"
  },
  {
    "ID": 12336,
    "Photo": "http://makerfaire.files.wordpress.com/2013/07/prt_200x280_1355863353.jpg"
  },
  {
    "ID": 12329,
    "Photo": "http://makerfaire.files.wordpress.com/2013/07/nesit-logo-circuit-boards-no-text-full-color.png"
  },
  {
    "ID": 12321,
    "Photo": "http://makerfaire.files.wordpress.com/2013/07/dscn21191.jpg"
  },
  {
    "ID": 12319,
    "Photo": "http://makerfaire.files.wordpress.com/2013/07/ahh-bbx-wm-1.jpg"
  },
  {
    "ID": 12316,
    "Photo": ""
  },
  {
    "ID": 12312,
    "Photo": "http://makerfaire.files.wordpress.com/2013/07/nyskyline4.jpg"
  },
  {
    "ID": 12302,
    "Photo": "http://makerfaire.files.wordpress.com/2013/07/img_20130511_080718.jpg"
  },
  {
    "ID": 12298,
    "Photo": "http://makerfaire.files.wordpress.com/2013/07/wetpong.jpg"
  },
  {
    "ID": 12294,
    "Photo": "http://makerfaire.files.wordpress.com/2013/07/2groprohousings.jpg"
  },
  {
    "ID": 12280,
    "Photo": "http://makerfaire.files.wordpress.com/2013/07/cre8time_blue_black.jpg"
  },
  {
    "ID": 12278,
    "Photo": "http://makerfaire.files.wordpress.com/2013/07/new-in-use.jpg"
  },
  {
    "ID": 12275,
    "Photo": "http://makerfaire.files.wordpress.com/2013/07/lemon-battery-ourworkshop-com-13.jpg"
  },
  {
    "ID": 12270,
    "Photo": "http://makerfaire.files.wordpress.com/2013/07/img_2682.jpg"
  },
  {
    "ID": 12268,
    "Photo": "http://makerfaire.files.wordpress.com/2013/07/3_800.jpg"
  },
  {
    "ID": 12263,
    "Photo": "http://makerfaire.files.wordpress.com/2013/07/mfny-photo.jpg"
  },
  {
    "ID": 12251,
    "Photo": "http://makerfaire.files.wordpress.com/2013/07/flowchart.png"
  },
  {
    "ID": 12246,
    "Photo": "http://makerfaire.files.wordpress.com/2013/07/emkrocket-2.jpg"
  },
  {
    "ID": 12239,
    "Photo": "http://makerfaire.files.wordpress.com/2013/07/fundacion_promedio_silla.jpg"
  },
  {
    "ID": 12237,
    "Photo": "http://makerfaire.files.wordpress.com/2013/07/maker-faire-nyc-pic-hellenga.jpg"
  },
  {
    "ID": 12234,
    "Photo": "http://makerfaire.files.wordpress.com/2013/07/threeform-image1.jpg"
  },
  {
    "ID": 12226,
    "Photo": "http://makerfaire.files.wordpress.com/2013/07/greek-toy-theater-project-001.jpg"
  },
  {
    "ID": 12222,
    "Photo": "http://makerfaire.files.wordpress.com/2013/07/cultivofotoconlogo.jpg"
  },
  {
    "ID": 12212,
    "Photo": "http://makerfaire.files.wordpress.com/2013/07/dsc00885_cropped.jpg"
  },
  {
    "ID": 12205,
    "Photo": "http://makerfaire.files.wordpress.com/2013/07/img_9904.jpg"
  },
  {
    "ID": 12198,
    "Photo": "http://makerfaire.files.wordpress.com/2013/07/social_gumball.png"
  },
  {
    "ID": 12195,
    "Photo": "http://makerfaire.files.wordpress.com/2013/07/superhero-lab.jpg"
  },
  {
    "ID": 12193,
    "Photo": "http://makerfaire.files.wordpress.com/2013/07/cn9d1m8.jpg"
  },
  {
    "ID": 12180,
    "Photo": "http://makerfaire.files.wordpress.com/2013/07/phoenix_clock.jpg"
  },
  {
    "ID": 12175,
    "Photo": "http://makerfaire.files.wordpress.com/2013/07/logo.png"
  },
  {
    "ID": 12173,
    "Photo": "http://makerfaire.files.wordpress.com/2013/07/robotphoto.jpg"
  },
  {
    "ID": 12171,
    "Photo": "http://makerfaire.files.wordpress.com/2013/07/alpac.jpg"
  },
  {
    "ID": 12163,
    "Photo": "http://makerfaire.files.wordpress.com/2013/07/tempsensingdress.jpg"
  },
  {
    "ID": 12161,
    "Photo": "http://makerfaire.files.wordpress.com/2013/07/scat.png"
  },
  {
    "ID": 12154,
    "Photo": "http://makerfaire.files.wordpress.com/2013/07/maker_faire_2013.jpg"
  },
  {
    "ID": 12152,
    "Photo": "http://makerfaire.files.wordpress.com/2013/07/img_5534.jpg"
  },
  {
    "ID": 12145,
    "Photo": "http://makerfaire.files.wordpress.com/2013/07/bholdable_white_logo.png"
  },
  {
    "ID": 12143,
    "Photo": "http://makerfaire.files.wordpress.com/2013/07/dan-wheelchair-device-overview-2013.jpg"
  },
  {
    "ID": 12140,
    "Photo": "http://makerfaire.files.wordpress.com/2013/07/pedalpoweredsynth.png"
  },
  {
    "ID": 12137,
    "Photo": "http://makerfaire.files.wordpress.com/2013/07/img_0314.jpg"
  },
  {
    "ID": 12132,
    "Photo": "http://makerfaire.files.wordpress.com/2013/07/img_00000197.jpg"
  },
  {
    "ID": 12121,
    "Photo": "http://makerfaire.files.wordpress.com/2013/07/farmhack-header_2_01.png"
  },
  {
    "ID": 12117,
    "Photo": "http://makerfaire.files.wordpress.com/2013/07/stephen-stuart-congo-by-hector-orellana-figment-nyc-620x465.jpeg"
  },
  {
    "ID": 12115,
    "Photo": "http://makerfaire.files.wordpress.com/2013/07/maikerfaire-foto.png"
  },
  {
    "ID": 12111,
    "Photo": "http://makerfaire.files.wordpress.com/2013/07/2013-07-10-17-20-531.jpg"
  },
  {
    "ID": 12108,
    "Photo": "http://makerfaire.files.wordpress.com/2013/07/dsc00657.jpg"
  },
  {
    "ID": 12104,
    "Photo": "http://makerfaire.files.wordpress.com/2013/07/logofloor.jpg"
  },
  {
    "ID": 12100,
    "Photo": "http://makerfaire.files.wordpress.com/2013/07/jenn_javier_installation.jpg"
  },
  {
    "ID": 12098,
    "Photo": "http://makerfaire.files.wordpress.com/2013/09/12098.jpg"
  },
  {
    "ID": 12096,
    "Photo": "http://makerfaire.files.wordpress.com/2013/09/12096.jpg"
  },
  {
    "ID": 12089,
    "Photo": "http://makerfaire.files.wordpress.com/2013/07/splash.jpg"
  },
  {
    "ID": 12085,
    "Photo": "http://makerfaire.files.wordpress.com/2013/07/715006648eff9b58c9fa75096b7756912.jpeg"
  },
  {
    "ID": 12079,
    "Photo": "http://makerfaire.files.wordpress.com/2013/07/kickstarter-4x3.png"
  },
  {
    "ID": 12077,
    "Photo": "http://makerfaire.files.wordpress.com/2013/07/dna1.jpg"
  },
  {
    "ID": 12072,
    "Photo": "http://makerfaire.files.wordpress.com/2013/07/pro06dlx2.jpg"
  },
  {
    "ID": 12067,
    "Photo": "http://makerfaire.files.wordpress.com/2013/07/img_20130726_155147.jpg"
  },
  {
    "ID": 12055,
    "Photo": "http://makerfaire.files.wordpress.com/2013/07/ccm-logo.png"
  },
  {
    "ID": 12052,
    "Photo": "http://makerfaire.files.wordpress.com/2013/07/pi_alcyone.jpg"
  },
  {
    "ID": 12049,
    "Photo": "http://makerfaire.files.wordpress.com/2013/07/cyclonecloseup2.jpg"
  },
  {
    "ID": 12043,
    "Photo": "http://makerfaire.files.wordpress.com/2013/07/2010-full-island.jpg"
  },
  {
    "ID": 12030,
    "Photo": "http://makerfaire.files.wordpress.com/2013/07/imag0052.jpg"
  },
  {
    "ID": 12019,
    "Photo": "http://makerfaire.files.wordpress.com/2013/07/13e08i24u_c_q.jpg"
  },
  {
    "ID": 12017,
    "Photo": "http://makerfaire.files.wordpress.com/2013/07/kickstarter-project-image-2-22-2012.jpg"
  },
  {
    "ID": 12009,
    "Photo": "http://makerfaire.files.wordpress.com/2013/07/photo1.jpg"
  },
  {
    "ID": 12007,
    "Photo": "http://makerfaire.files.wordpress.com/2013/07/lock_pick.jpg"
  },
  {
    "ID": 12003,
    "Photo": "http://makerfaire.files.wordpress.com/2013/07/img_9258s.jpg"
  },
  {
    "ID": 12000,
    "Photo": "http://makerfaire.files.wordpress.com/2013/07/mf-comp2.jpg"
  },
  {
    "ID": 11996,
    "Photo": "http://makerfaire.files.wordpress.com/2013/07/2013-05-05-18-52-47.jpg"
  },
  {
    "ID": 11994,
    "Photo": "http://makerfaire.files.wordpress.com/2013/07/scentrproto2.jpg"
  },
  {
    "ID": 11987,
    "Photo": "http://makerfaire.files.wordpress.com/2013/07/kit1.jpg"
  },
  {
    "ID": 11978,
    "Photo": "http://makerfaire.files.wordpress.com/2013/07/moti_4_adjusted_web.jpg"
  },
  {
    "ID": 11972,
    "Photo": "http://makerfaire.files.wordpress.com/2013/07/friendshiploom.jpg"
  },
  {
    "ID": 11963,
    "Photo": "http://makerfaire.files.wordpress.com/2013/07/copy-2-of-img_4469.jpg"
  },
  {
    "ID": 11951,
    "Photo": "http://makerfaire.files.wordpress.com/2013/07/ultrasonic_cane.jpg"
  },
  {
    "ID": 11947,
    "Photo": "http://makerfaire.files.wordpress.com/2013/07/photo-31.jpg"
  },
  {
    "ID": 11942,
    "Photo": "http://makerfaire.files.wordpress.com/2013/07/inmoov_image.jpg"
  },
  {
    "ID": 11932,
    "Photo": "http://makerfaire.files.wordpress.com/2013/07/how-do-you-define-making-day-1.jpg"
  },
  {
    "ID": 11923,
    "Photo": "http://makerfaire.files.wordpress.com/2013/07/make-your-own-soap.jpg"
  },
  {
    "ID": 11920,
    "Photo": "http://makerfaire.files.wordpress.com/2013/07/the-ball.jpg"
  },
  {
    "ID": 11917,
    "Photo": "http://makerfaire.files.wordpress.com/2013/07/screen-shot-2013-07-28-at-11-28-26-am.png"
  },
  {
    "ID": 11914,
    "Photo": "http://makerfaire.files.wordpress.com/2013/07/makefaire_logo.jpg"
  },
  {
    "ID": 11911,
    "Photo": "http://makerfaire.files.wordpress.com/2013/07/2013-07-17-20-43-44.jpg"
  },
  {
    "ID": 11908,
    "Photo": "http://makerfaire.files.wordpress.com/2013/07/bus_3d_y.jpg"
  },
  {
    "ID": 11898,
    "Photo": "http://makerfaire.files.wordpress.com/2013/07/all-kits.jpeg"
  },
  {
    "ID": 11893,
    "Photo": "http://makerfaire.files.wordpress.com/2013/07/serenity.jpg"
  },
  {
    "ID": 11881,
    "Photo": "http://makerfaire.files.wordpress.com/2013/07/purple-vision.jpg"
  },
  {
    "ID": 11876,
    "Photo": "http://makerfaire.files.wordpress.com/2013/07/72688_10101779412100689_1787776912_n-1.jpg"
  },
  {
    "ID": 11871,
    "Photo": "http://makerfaire.files.wordpress.com/2013/07/march.jpg"
  },
  {
    "ID": 11867,
    "Photo": "http://makerfaire.files.wordpress.com/2013/07/img_0857.jpg"
  },
  {
    "ID": 11863,
    "Photo": "http://makerfaire.files.wordpress.com/2013/07/performerphoto1.png"
  },
  {
    "ID": 11854,
    "Photo": ""
  },
  {
    "ID": 11851,
    "Photo": "http://makerfaire.files.wordpress.com/2013/07/pc1500.png"
  },
  {
    "ID": 11848,
    "Photo": "http://makerfaire.files.wordpress.com/2013/07/dlp3dprinter.jpg"
  },
  {
    "ID": 11836,
    "Photo": "http://makerfaire.files.wordpress.com/2013/07/dewey-self-port.jpg"
  },
  {
    "ID": 11820,
    "Photo": "http://makerfaire.files.wordpress.com/2013/07/browsercize_th.jpg"
  },
  {
    "ID": 11803,
    "Photo": "http://makerfaire.files.wordpress.com/2013/07/tardis_crop.jpg"
  },
  {
    "ID": 11792,
    "Photo": "http://makerfaire.files.wordpress.com/2013/07/scrapingsoundwave1.jpg"
  },
  {
    "ID": 11785,
    "Photo": "http://makerfaire.files.wordpress.com/2013/07/walking-legs-nice.jpg"
  },
  {
    "ID": 11782,
    "Photo": "http://makerfaire.files.wordpress.com/2013/07/heart_matrix.jpg"
  },
  {
    "ID": 11776,
    "Photo": "http://makerfaire.files.wordpress.com/2013/07/ohmwrestlinglogo-2.jpg"
  },
  {
    "ID": 11764,
    "Photo": "http://makerfaire.files.wordpress.com/2013/09/frontier_identity.jpg"
  },
  {
    "ID": 11753,
    "Photo": "http://makerfaire.files.wordpress.com/2013/07/img_1662.jpg"
  },
  {
    "ID": 11751,
    "Photo": "http://makerfaire.files.wordpress.com/2013/07/photo-2.jpg"
  },
  {
    "ID": 11747,
    "Photo": "http://makerfaire.files.wordpress.com/2013/07/img_2734.jpg"
  },
  {
    "ID": 11738,
    "Photo": "http://makerfaire.files.wordpress.com/2013/07/800px-fedora-printed-thumb.jpg"
  },
  {
    "ID": 11731,
    "Photo": "http://makerfaire.files.wordpress.com/2013/07/image8.jpg"
  },
  {
    "ID": 11721,
    "Photo": "http://makerfaire.files.wordpress.com/2013/07/project_photo.png"
  },
  {
    "ID": 11718,
    "Photo": "http://makerfaire.files.wordpress.com/2013/07/9370256725_348cfe24bb.jpg"
  },
  {
    "ID": 11716,
    "Photo": "http://makerfaire.files.wordpress.com/2013/07/3dmonstr-6571-500x500.jpg"
  },
  {
    "ID": 11713,
    "Photo": "http://makerfaire.files.wordpress.com/2013/07/osage-tool-caddy.jpg"
  },
  {
    "ID": 11709,
    "Photo": "http://makerfaire.files.wordpress.com/2013/07/dsc1781-girl.jpg"
  },
  {
    "ID": 11705,
    "Photo": "http://makerfaire.files.wordpress.com/2013/07/blr1.jpg"
  },
  {
    "ID": 11703,
    "Photo": "http://makerfaire.files.wordpress.com/2013/07/classroom-engagement-scores-01.jpg"
  },
  {
    "ID": 11697,
    "Photo": "http://makerfaire.files.wordpress.com/2013/07/cathedralexterior.jpg"
  },
  {
    "ID": 11692,
    "Photo": "http://makerfaire.files.wordpress.com/2013/07/mcorps_logo_new.png"
  },
  {
    "ID": 11689,
    "Photo": "http://makerfaire.files.wordpress.com/2013/07/labs.png"
  },
  {
    "ID": 11686,
    "Photo": "http://makerfaire.files.wordpress.com/2013/07/promopic.png"
  },
  {
    "ID": 11680,
    "Photo": "http://makerfaire.files.wordpress.com/2013/09/inflatable-robot.jpg"
  },
  {
    "ID": 11668,
    "Photo": "http://makerfaire.files.wordpress.com/2013/07/maker-fair.png"
  },
  {
    "ID": 11659,
    "Photo": "http://makerfaire.files.wordpress.com/2013/07/img_20130520_040223.jpg"
  },
  {
    "ID": 11651,
    "Photo": "http://makerfaire.files.wordpress.com/2013/07/img_46831.jpg"
  },
  {
    "ID": 11645,
    "Photo": "http://makerfaire.files.wordpress.com/2013/07/image3.jpg"
  },
  {
    "ID": 11638,
    "Photo": "http://makerfaire.files.wordpress.com/2013/07/home.png"
  },
  {
    "ID": 11603,
    "Photo": "http://makerfaire.files.wordpress.com/2013/07/img_0379.jpg"
  },
  {
    "ID": 11599,
    "Photo": "http://makerfaire.files.wordpress.com/2013/07/gopr1732.jpg"
  },
  {
    "ID": 11596,
    "Photo": "http://makerfaire.files.wordpress.com/2013/07/7858798540_001af234c6_o.jpg"
  },
  {
    "ID": 11590,
    "Photo": "http://makerfaire.files.wordpress.com/2013/07/bramsonfrontdoor2.jpg"
  },
  {
    "ID": 11584,
    "Photo": "http://makerfaire.files.wordpress.com/2013/07/img_2239.jpg"
  },
  {
    "ID": 11581,
    "Photo": "http://makerfaire.files.wordpress.com/2013/07/mozillahivenyclogo.jpeg"
  },
  {
    "ID": 11578,
    "Photo": "http://makerfaire.files.wordpress.com/2013/07/mars_rover.jpg"
  },
  {
    "ID": 11575,
    "Photo": "http://makerfaire.files.wordpress.com/2013/07/arcbotics-logo.jpg"
  },
  {
    "ID": 11570,
    "Photo": "http://makerfaire.files.wordpress.com/2013/07/fig_title2.png"
  },
  {
    "ID": 11567,
    "Photo": ""
  },
  {
    "ID": 11546,
    "Photo": "http://makerfaire.files.wordpress.com/2013/07/9057224167_7be96abf4e_k.jpg"
  },
  {
    "ID": 11541,
    "Photo": "http://makerfaire.files.wordpress.com/2013/07/dsc01515.jpg"
  },
  {
    "ID": 11538,
    "Photo": ""
  },
  {
    "ID": 11532,
    "Photo": "http://makerfaire.files.wordpress.com/2013/07/seriesonehero.png"
  },
  {
    "ID": 11524,
    "Photo": "http://makerfaire.files.wordpress.com/2013/07/booth.jpg"
  },
  {
    "ID": 11515,
    "Photo": "http://makerfaire.files.wordpress.com/2013/07/coursemodel2.jpg"
  },
  {
    "ID": 11500,
    "Photo": ""
  },
  {
    "ID": 11494,
    "Photo": "http://makerfaire.files.wordpress.com/2013/07/simpson_display_large.jpg"
  },
  {
    "ID": 11484,
    "Photo": "http://makerfaire.files.wordpress.com/2013/07/makerjawn.png"
  },
  {
    "ID": 11479,
    "Photo": "http://makerfaire.files.wordpress.com/2013/07/themakerguy.jpg"
  },
  {
    "ID": 11467,
    "Photo": "http://makerfaire.files.wordpress.com/2013/07/diyodelogolarge.png"
  },
  {
    "ID": 11463,
    "Photo": "http://makerfaire.files.wordpress.com/2013/07/led-module1.jpg"
  },
  {
    "ID": 11456,
    "Photo": "http://makerfaire.files.wordpress.com/2013/07/cover-30px-01.png"
  },
  {
    "ID": 11450,
    "Photo": "http://makerfaire.files.wordpress.com/2013/07/2013_0718-fixing-session-cover-01.jpg"
  },
  {
    "ID": 11446,
    "Photo": "http://makerfaire.files.wordpress.com/2013/07/mulitree.jpg"
  },
  {
    "ID": 11435,
    "Photo": "http://makerfaire.files.wordpress.com/2013/07/metlogoverold.png"
  },
  {
    "ID": 11431,
    "Photo": "http://makerfaire.files.wordpress.com/2013/07/products_of_design.jpg"
  },
  {
    "ID": 11429,
    "Photo": "http://makerfaire.files.wordpress.com/2013/07/cacu.jpg"
  },
  {
    "ID": 11426,
    "Photo": "http://makerfaire.files.wordpress.com/2013/07/robox.jpg"
  },
  {
    "ID": 11423,
    "Photo": "http://makerfaire.files.wordpress.com/2013/07/liabilityrisk.jpg"
  },
  {
    "ID": 11420,
    "Photo": "http://makerfaire.files.wordpress.com/2013/07/isf-side-view.jpg"
  },
  {
    "ID": 11412,
    "Photo": "http://makerfaire.files.wordpress.com/2013/07/img_2023.jpg"
  },
  {
    "ID": 11410,
    "Photo": "http://makerfaire.files.wordpress.com/2013/07/di_wire_2_hero11.jpg"
  },
  {
    "ID": 11407,
    "Photo": "http://makerfaire.files.wordpress.com/2013/07/3dposhwreprap1.png"
  },
  {
    "ID": 11402,
    "Photo": "http://makerfaire.files.wordpress.com/2013/07/full_build_1_preview_featured.jpg"
  },
  {
    "ID": 11399,
    "Photo": "http://makerfaire.files.wordpress.com/2013/07/maker-faire.jpg"
  },
  {
    "ID": 11388,
    "Photo": "http://makerfaire.files.wordpress.com/2013/07/dsc_0126.jpg"
  },
  {
    "ID": 11380,
    "Photo": "http://makerfaire.files.wordpress.com/2013/08/nazca-beats-v2.jpg"
  },
  {
    "ID": 11377,
    "Photo": "http://makerfaire.files.wordpress.com/2013/07/dsc_2218-001.jpg"
  },
  {
    "ID": 11373,
    "Photo": "http://makerfaire.files.wordpress.com/2013/07/header-7-17-13.jpg"
  },
  {
    "ID": 11369,
    "Photo": "http://makerfaire.files.wordpress.com/2013/07/butterfly.png"
  },
  {
    "ID": 11366,
    "Photo": "http://makerfaire.files.wordpress.com/2013/07/screen-shot-2013-07-27-at-3-38-24-pm.png"
  },
  {
    "ID": 11363,
    "Photo": "http://makerfaire.files.wordpress.com/2013/07/village.jpg"
  },
  {
    "ID": 11358,
    "Photo": "http://makerfaire.files.wordpress.com/2013/07/130612-9227a.jpg"
  },
  {
    "ID": 11352,
    "Photo": "http://makerfaire.files.wordpress.com/2013/07/maker.jpg"
  },
  {
    "ID": 11347,
    "Photo": ""
  },
  {
    "ID": 11337,
    "Photo": "http://makerfaire.files.wordpress.com/2013/07/582534_388208384542951_1224258021_n.jpg"
  },
  {
    "ID": 11335,
    "Photo": "http://makerfaire.files.wordpress.com/2013/07/arg-animation-500x3751.gif"
  },
  {
    "ID": 11329,
    "Photo": "http://makerfaire.files.wordpress.com/2013/07/ken-butler-150dpi-dlevere.jpg"
  },
  {
    "ID": 11325,
    "Photo": "http://makerfaire.files.wordpress.com/2013/07/fist-full-of-bulbs.jpg"
  },
  {
    "ID": 11322,
    "Photo": "http://makerfaire.files.wordpress.com/2013/07/rover.jpg"
  },
  {
    "ID": 11319,
    "Photo": "http://makerfaire.files.wordpress.com/2013/07/img_2437.jpg"
  },
  {
    "ID": 11313,
    "Photo": "http://makerfaire.files.wordpress.com/2013/07/shipbuilder.jpg"
  },
  {
    "ID": 11308,
    "Photo": "http://makerfaire.files.wordpress.com/2013/07/photo.jpg"
  },
  {
    "ID": 11301,
    "Photo": "http://makerfaire.files.wordpress.com/2013/07/windfarm-goggles.jpg"
  },
  {
    "ID": 11297,
    "Photo": "http://makerfaire.files.wordpress.com/2013/07/e3-left-side-picture.jpg"
  },
  {
    "ID": 11294,
    "Photo": "http://makerfaire.files.wordpress.com/2013/07/dsc_00241.jpg"
  },
  {
    "ID": 11270,
    "Photo": "http://makerfaire.files.wordpress.com/2013/07/8504897246_ce0e043939_h.jpg"
  },
  {
    "ID": 11253,
    "Photo": "http://makerfaire.files.wordpress.com/2013/07/cube-copy2.jpeg"
  },
  {
    "ID": 11235,
    "Photo": "http://makerfaire.files.wordpress.com/2013/07/dsc_3349.jpg"
  },
  {
    "ID": 11225,
    "Photo": "http://makerfaire.files.wordpress.com/2013/07/img_3574-resized.png"
  },
  {
    "ID": 11218,
    "Photo": "http://makerfaire.files.wordpress.com/2013/07/936304_10151597629156488_382089308_n.jpg"
  },
  {
    "ID": 11204,
    "Photo": "http://makerfaire.files.wordpress.com/2013/08/maker-faire-screenshot.png"
  },
  {
    "ID": 11200,
    "Photo": "http://makerfaire.files.wordpress.com/2013/07/image1.jpg"
  },
  {
    "ID": 11186,
    "Photo": "http://makerfaire.files.wordpress.com/2013/07/eff-logo-name-stack-2b1.png"
  },
  {
    "ID": 11182,
    "Photo": ""
  },
  {
    "ID": 11175,
    "Photo": "http://makerfaire.files.wordpress.com/2013/07/ditto-front.jpg"
  },
  {
    "ID": 11170,
    "Photo": "http://makerfaire.files.wordpress.com/2013/07/trashcan-man.jpg"
  },
  {
    "ID": 11155,
    "Photo": "http://makerfaire.files.wordpress.com/2013/07/bpllogo.jpg"
  },
  {
    "ID": 11147,
    "Photo": "http://makerfaire.files.wordpress.com/2013/07/bluestamp_dy_cropped.jpg"
  },
  {
    "ID": 11142,
    "Photo": "http://makerfaire.files.wordpress.com/2013/07/freematics_shield_prototype.jpg"
  },
  {
    "ID": 11137,
    "Photo": "http://makerfaire.files.wordpress.com/2013/07/photo-jul-12-4-01-28-pm.jpg"
  },
  {
    "ID": 11133,
    "Photo": "http://makerfaire.files.wordpress.com/2013/07/robot_twigs.jpg"
  },
  {
    "ID": 11118,
    "Photo": "http://makerfaire.files.wordpress.com/2013/07/mf2013_postcard1.jpg"
  },
  {
    "ID": 11113,
    "Photo": "http://makerfaire.files.wordpress.com/2013/07/alyosha-mf.jpg"
  },
  {
    "ID": 11106,
    "Photo": "http://makerfaire.files.wordpress.com/2013/07/screenshot.png"
  },
  {
    "ID": 11100,
    "Photo": "http://makerfaire.files.wordpress.com/2013/07/webradioproject1.jpg"
  },
  {
    "ID": 11091,
    "Photo": "http://makerfaire.files.wordpress.com/2013/07/2012-08-22-11-15-27.jpg"
  },
  {
    "ID": 11089,
    "Photo": ""
  },
  {
    "ID": 11086,
    "Photo": "http://makerfaire.files.wordpress.com/2013/07/clone_front.jpg"
  },
  {
    "ID": 11075,
    "Photo": "http://makerfaire.files.wordpress.com/2013/07/makerfaire.png"
  },
  {
    "ID": 11071,
    "Photo": "http://makerfaire.files.wordpress.com/2013/07/maker-faire-20132.jpg"
  },
  {
    "ID": 11059,
    "Photo": "http://makerfaire.files.wordpress.com/2013/07/collage2photo.jpg"
  },
  {
    "ID": 11051,
    "Photo": "http://makerfaire.files.wordpress.com/2013/07/igem-2013-1.jpg"
  },
  {
    "ID": 11049,
    "Photo": ""
  },
  {
    "ID": 11040,
    "Photo": "http://makerfaire.files.wordpress.com/2013/07/robofun_logo_big1.jpg"
  },
  {
    "ID": 11037,
    "Photo": "http://makerfaire.files.wordpress.com/2013/07/ycbg.jpeg"
  },
  {
    "ID": 11032,
    "Photo": "http://makerfaire.files.wordpress.com/2013/07/20130709_121446.jpg"
  },
  {
    "ID": 11012,
    "Photo": "http://makerfaire.files.wordpress.com/2013/07/024.jpg"
  },
  {
    "ID": 11006,
    "Photo": "http://makerfaire.files.wordpress.com/2013/07/imp2.jpg"
  },
  {
    "ID": 11003,
    "Photo": "http://makerfaire.files.wordpress.com/2013/07/4thofjuly_gbba.jpg"
  },
  {
    "ID": 11000,
    "Photo": "http://makerfaire.files.wordpress.com/2013/07/img_2458.jpg"
  },
  {
    "ID": 10988,
    "Photo": ""
  },
  {
    "ID": 10984,
    "Photo": "http://makerfaire.files.wordpress.com/2013/07/mildred8.jpg"
  },
  {
    "ID": 10982,
    "Photo": "http://makerfaire.files.wordpress.com/2013/07/cropped-i_lug_lyndhurst_2012.jpg"
  },
  {
    "ID": 10962,
    "Photo": "http://makerfaire.files.wordpress.com/2013/07/crochet_cube1.png"
  },
  {
    "ID": 10959,
    "Photo": "http://makerfaire.files.wordpress.com/2013/07/abprojectphoto.jpg"
  },
  {
    "ID": 10954,
    "Photo": "http://makerfaire.files.wordpress.com/2013/07/logi-pi-bone-mark1.jpg"
  },
  {
    "ID": 10952,
    "Photo": "http://makerfaire.files.wordpress.com/2013/07/fun-for-all.jpg"
  },
  {
    "ID": 10949,
    "Photo": "http://makerfaire.files.wordpress.com/2013/07/imag1192.jpg"
  },
  {
    "ID": 10944,
    "Photo": "http://makerfaire.files.wordpress.com/2013/07/bbot-front.jpg"
  },
  {
    "ID": 10904,
    "Photo": "http://makerfaire.files.wordpress.com/2013/07/chopstickingcover.jpg"
  },
  {
    "ID": 10895,
    "Photo": "http://makerfaire.files.wordpress.com/2013/07/img_62921.jpg"
  },
  {
    "ID": 10887,
    "Photo": "http://makerfaire.files.wordpress.com/2013/07/picture1.jpg"
  },
  {
    "ID": 10885,
    "Photo": "http://makerfaire.files.wordpress.com/2013/06/maker_bill_and_gary.jpg"
  },
  {
    "ID": 10882,
    "Photo": "http://makerfaire.files.wordpress.com/2013/07/simplify3d_project_photo_r2_sm.jpg"
  },
  {
    "ID": 10879,
    "Photo": "http://makerfaire.files.wordpress.com/2013/06/img_1873.jpg"
  },
  {
    "ID": 10871,
    "Photo": "http://makerfaire.files.wordpress.com/2013/06/pop-up-dayna.jpg"
  },
  {
    "ID": 10868,
    "Photo": "http://makerfaire.files.wordpress.com/2013/06/appliedinspirationskits.jpg"
  },
  {
    "ID": 10865,
    "Photo": "http://makerfaire.files.wordpress.com/2013/06/kap.png"
  },
  {
    "ID": 10862,
    "Photo": "http://makerfaire.files.wordpress.com/2013/06/digital-being-02.jpg"
  },
  {
    "ID": 10859,
    "Photo": "http://makerfaire.files.wordpress.com/2013/06/floid_system_diagram2.png"
  },
  {
    "ID": 10853,
    "Photo": "http://makerfaire.files.wordpress.com/2013/09/10853.jpg"
  },
  {
    "ID": 10846,
    "Photo": ""
  },
  {
    "ID": 10844,
    "Photo": "http://makerfaire.files.wordpress.com/2013/06/owlmkrfaire.jpg"
  },
  {
    "ID": 10839,
    "Photo": "http://makerfaire.files.wordpress.com/2013/06/balam-mkrsfaire.jpg"
  },
  {
    "ID": 10829,
    "Photo": "http://makerfaire.files.wordpress.com/2013/06/logo-with-dilly-design-2.jpg"
  },
  {
    "ID": 10826,
    "Photo": "http://makerfaire.files.wordpress.com/2013/06/barcode-gel.jpg"
  },
  {
    "ID": 10819,
    "Photo": "http://makerfaire.files.wordpress.com/2013/06/schrodinger.jpg"
  },
  {
    "ID": 10801,
    "Photo": "http://makerfaire.files.wordpress.com/2013/06/soccer2013.png"
  },
  {
    "ID": 10798,
    "Photo": "http://makerfaire.files.wordpress.com/2013/06/img_4384-1040x320.jpg"
  },
  {
    "ID": 10794,
    "Photo": "http://makerfaire.files.wordpress.com/2013/07/photo-12.jpg"
  },
  {
    "ID": 10774,
    "Photo": "http://makerfaire.files.wordpress.com/2013/06/image2.jpg"
  },
  {
    "ID": 10771,
    "Photo": "http://makerfaire.files.wordpress.com/2013/06/c-made_cardboard_toys.gif"
  },
  {
    "ID": 10768,
    "Photo": "http://makerfaire.files.wordpress.com/2013/07/background21.png"
  },
  {
    "ID": 10766,
    "Photo": "http://makerfaire.files.wordpress.com/2013/06/setup1.jpg"
  },
  {
    "ID": 10762,
    "Photo": "http://makerfaire.files.wordpress.com/2013/06/lightportal_bare_diagram.jpg"
  },
  {
    "ID": 10759,
    "Photo": "http://makerfaire.files.wordpress.com/2013/06/sashimi-12-crop-3.jpg"
  },
  {
    "ID": 10756,
    "Photo": "http://makerfaire.files.wordpress.com/2013/06/img_1036.jpg"
  },
  {
    "ID": 10750,
    "Photo": "http://makerfaire.files.wordpress.com/2013/06/trailer-park_mobile-public-park.jpg"
  },
  {
    "ID": 10742,
    "Photo": "http://makerfaire.files.wordpress.com/2013/06/photo.jpg"
  },
  {
    "ID": 10739,
    "Photo": "http://makerfaire.files.wordpress.com/2013/06/video_sans-video_game.jpg"
  },
  {
    "ID": 10736,
    "Photo": "http://makerfaire.files.wordpress.com/2013/06/dscf03191.jpg"
  },
  {
    "ID": 10701,
    "Photo": "http://makerfaire.files.wordpress.com/2013/06/fracturedatlassquarelogo.jpg"
  },
  {
    "ID": 10693,
    "Photo": "http://makerfaire.files.wordpress.com/2013/07/brian-and-shortest-for-email.jpg"
  },
  {
    "ID": 10687,
    "Photo": "http://makerfaire.files.wordpress.com/2013/06/img_0968.jpg"
  },
  {
    "ID": 10684,
    "Photo": "http://makerfaire.files.wordpress.com/2013/06/arduino-project.jpg"
  },
  {
    "ID": 10681,
    "Photo": "http://makerfaire.files.wordpress.com/2013/07/xronos_showcase_red_2-1.jpg"
  },
  {
    "ID": 10672,
    "Photo": "http://makerfaire.files.wordpress.com/2013/06/mf_branding_v01.jpg"
  },
  {
    "ID": 10669,
    "Photo": "http://makerfaire.files.wordpress.com/2013/06/mf-nyc-2012-02.jpg"
  },
  {
    "ID": 10666,
    "Photo": "http://makerfaire.files.wordpress.com/2013/06/3x3_square_front.jpg"
  },
  {
    "ID": 10659,
    "Photo": "http://makerfaire.files.wordpress.com/2013/06/253612_579149538762740_676404000_n.jpg"
  },
  {
    "ID": 10645,
    "Photo": "http://makerfaire.files.wordpress.com/2013/06/lumityper.jpeg"
  },
  {
    "ID": 10638,
    "Photo": "http://makerfaire.files.wordpress.com/2013/06/tvcogcolor750px.jpg"
  },
  {
    "ID": 10601,
    "Photo": "http://makerfaire.files.wordpress.com/2013/06/logo_padded1.png"
  },
  {
    "ID": 10597,
    "Photo": "http://makerfaire.files.wordpress.com/2013/06/education.jpg"
  },
  {
    "ID": 10590,
    "Photo": "http://makerfaire.files.wordpress.com/2013/06/colaboratoryunis.jpg"
  },
  {
    "ID": 10587,
    "Photo": "http://makerfaire.files.wordpress.com/2013/06/1.jpg"
  },
  {
    "ID": 10584,
    "Photo": "http://makerfaire.files.wordpress.com/2013/09/10584.jpg"
  },
  {
    "ID": 10574,
    "Photo": "http://makerfaire.files.wordpress.com/2013/06/20130518_101512.jpg"
  },
  {
    "ID": 10566,
    "Photo": "http://makerfaire.files.wordpress.com/2013/06/imgcollage34162.jpg"
  },
  {
    "ID": 10561,
    "Photo": "http://makerfaire.files.wordpress.com/2013/06/terra-jet-pic_youtube.jpg"
  },
  {
    "ID": 10558,
    "Photo": "http://makerfaire.files.wordpress.com/2013/06/concept.jpg"
  },
  {
    "ID": 10555,
    "Photo": "http://makerfaire.files.wordpress.com/2013/06/leaf-couture.jpg"
  },
  {
    "ID": 10552,
    "Photo": "http://makerfaire.files.wordpress.com/2013/06/photo-24.jpg"
  },
  {
    "ID": 10548,
    "Photo": "http://makerfaire.files.wordpress.com/2013/06/ron-dolin.jpg"
  },
  {
    "ID": 10541,
    "Photo": "http://makerfaire.files.wordpress.com/2013/06/photo-6.jpg"
  },
  {
    "ID": 10538,
    "Photo": "http://makerfaire.files.wordpress.com/2013/06/dataglove.jpeg"
  },
  {
    "ID": 10533,
    "Photo": "http://makerfaire.files.wordpress.com/2013/06/calchwmedley.jpg"
  },
  {
    "ID": 10525,
    "Photo": "http://makerfaire.files.wordpress.com/2013/06/intrige1.jpg"
  },
  {
    "ID": 10515,
    "Photo": "http://makerfaire.files.wordpress.com/2013/06/table_installed1.jpg"
  },
  {
    "ID": 10509,
    "Photo": "http://makerfaire.files.wordpress.com/2013/06/ks_cloudmaker.jpg"
  },
  {
    "ID": 10492,
    "Photo": "http://makerfaire.files.wordpress.com/2013/06/2012ieee_mfbooth.jpg"
  },
  {
    "ID": 10485,
    "Photo": "http://makerfaire.files.wordpress.com/2013/06/screen-shot-2013-06-06-at-10-08-06-pm.png"
  },
  {
    "ID": 10480,
    "Photo": "http://makerfaire.files.wordpress.com/2013/06/mybell3-01.png"
  },
  {
    "ID": 10465,
    "Photo": "http://makerfaire.files.wordpress.com/2013/06/entry-4.jpg"
  },
  {
    "ID": 10461,
    "Photo": "http://makerfaire.files.wordpress.com/2013/06/museumit_hires.jpg"
  },
  {
    "ID": 10457,
    "Photo": "http://makerfaire.files.wordpress.com/2013/06/img_0924.jpg"
  },
  {
    "ID": 6799,
    "Photo": "http://makerfaire.files.wordpress.com/2013/05/bbsf_bannergeneric1.jpg"
  }
]